pyspark_fixtures/__init__.py
pyspark_fixtures/fixtures.py
pyspark_fixtures/helpers.py
pyspark_fixtures/py.typed
pyspark_fixtures-2025.1.0rc3.dist-info/METADATA
pyspark_fixtures-2025.1.0rc3.dist-info/WHEEL
pyspark_fixtures-2025.1.0rc3.dist-info/top_level.txt
pyspark_fixtures-2025.1.0rc3.dist-info/RECORD
