Metadata-Version: 2.4
Name: pyspark-fixtures
Version: 2025.1.0rc3
Summary: Simple unit testing for PySpark jobs with readable fixtures for humans and machines, plus helpers to eliminate boilerplate
Author-email: Juan Pablo Guereca <juanpablo@guereca.com>
License: MIT
Keywords: pyspark,fixtures,tests,readable
Requires-Python: >=3.10
Requires-Dist: pyspark>=3.3.0
